AUTHORS
LICENSE
MANIFEST.in
README.rst
setup.py
Ahem.egg-info/PKG-INFO
Ahem.egg-info/SOURCES.txt
Ahem.egg-info/dependency_links.txt
Ahem.egg-info/requires.txt
Ahem.egg-info/top_level.txt
ahem/__init__.py
ahem/admin.py
ahem/backends.py
ahem/loader.py
ahem/models.py
ahem/notification.py
ahem/scopes.py
ahem/settings.py
ahem/tasks.py
ahem/triggers.py
ahem/utils.py