Metadata-Version: 1.1
Name: Ahem
Version: 0.2
Summary: Simple, but rich, declarative notification framework for Django
Home-page: https://github.com/Axilent/Ahem
Author: Loren Davie
Author-email: code@axilent.com
License: BSD
Platform: UNKNOWN
Classifier: Development Status :: 2 - Pre-Alpha
Classifier: Environment :: Web Environment
Classifier: Intended Audience :: Developers
Classifier: License :: OSI Approved :: MIT License
Classifier: Programming Language :: Python
Classifier: Topic :: Software Development :: Libraries :: Python Modules
